{
    "components": {
        "ltm": {
            "endpoints": {
                "pinning": {
                    "uri": "/mgmt/cm/adc-core/working-config/root-node" 
                },
                "deploy":  {
                    "uri": "/mgmt/cm/adc-core/tasks/deploy-configuration"
                },
                "sslCertReferences": {
                    "uri": "/mgmt/cm/adc-core/working-config/sys/file/ssl-cert"
                },
                "sslKeyReferences": {
                    "uri": "/mgmt/cm/adc-core/working-config/sys/file/ssl-key"
                },
                "iruleReferences": {
                    "uri": "/mgmt/cm/adc-core/working-config/ltm/rule"
                }       
            }
        },
        "shared_security": {
            "endpoints": {
                "pinning": {
                    "uri": "/mgmt/cm/security-shared/working-config/shared-root-nodes"
                },
                "deploy": {
                    "uri": "/mgmt/cm/security-shared/tasks/deploy-configuration"
                },
                "logProfileReferences": {
                    "uri": "/mgmt/cm/security-shared/working-config/log-profiles"
                }         
            }
        },
        "asm": {
            "endpoints": {
                "pinning": {
                    "uri": "/mgmt/cm/asm/working-config/virtual-servers"
                },
                "deploy": {
                    "uri": "/mgmt/cm/asm/tasks/deploy-configuration"
                },
                "attachedPoliciesReferences": {
                    "uri": "/mgmt/cm/asm/working-config/policies"
                }         
            }
        }
    }
}